furthermaths/__init__.py
furthermaths/abs_val.py
furthermaths/add_sub.py
furthermaths/angle_units.py
furthermaths/area.py
furthermaths/averages.py
furthermaths/constants.py
furthermaths/cube_root.py
furthermaths/digit_sum.py
furthermaths/distance.py
furthermaths/equality.py
furthermaths/eratosthenes.py
furthermaths/exponential.py
furthermaths/factorial.py
furthermaths/nth_root.py
furthermaths/perfect_numbers.py
furthermaths/perm_combs.py
furthermaths/prime_factors.py
furthermaths/rounding.py
furthermaths/square_root.py
furthermaths/surface_area.py
furthermaths/trigonometry.py
furthermaths/volume.py
furthermaths/complex/__init__.py
furthermaths/matrices/Matrix.py
furthermaths/matrices/__init__.py
furthermaths/series/__init__.py
furthermaths/series/arithmetic.py
furthermaths/series/fibbonacci.py
furthermaths/series/geometric.py
furthermaths/series/harmonic.py
furthermaths/series/hexagonal_numbers.py
furthermaths/vectors/Vectors.py
furthermaths/vectors/__init__.py
furthermaths-0.1.2.dist-info/LICENSE.txt
furthermaths-0.1.2.dist-info/METADATA
furthermaths-0.1.2.dist-info/WHEEL
furthermaths-0.1.2.dist-info/top_level.txt
furthermaths-0.1.2.dist-info/RECORD
