Metadata-Version: 2.1
Name: furthermaths
Version: 0.1.2
Summary: An extension to the pre-installed and packaged python default maths library
Home-page: UNKNOWN
License: MIT
Platform: UNKNOWN
Classifier: Programming Language :: Python :: 3.10
Requires-Python: >=3.10.0
License-File: LICENSE.txt
